pyvsc-0.9.4.19342806556.dist-info/licenses/LICENSE
vsc/__init__.py
vsc/attrs.py
vsc/constraints.py
vsc/coverage.py
vsc/methods.py
vsc/rand_obj.py
vsc/types.py
vsc/impl/__init__.py
vsc/impl/constraint_proxy.py
vsc/impl/coverage_registry.py
vsc/impl/covergroup_int.py
vsc/impl/ctor.py
vsc/impl/enum_info.py
vsc/impl/expr_mode.py
vsc/impl/generator_int.py
vsc/impl/options.py
vsc/impl/randobj_int.py
vsc/impl/type_options.py
vsc/impl/vscobj_int.py
vsc/impl/wildcard_bin_factory.py
vsc/model/__init__.py
vsc/model/bin_expr_type.py
vsc/model/constraint_block_model.py
vsc/model/constraint_dist_model.py
vsc/model/constraint_dist_scope_model.py
vsc/model/constraint_expr_model.py
vsc/model/constraint_foreach_model.py
vsc/model/constraint_if_else_model.py
vsc/model/constraint_implies_model.py
vsc/model/constraint_inline_scope_model.py
vsc/model/constraint_model.py
vsc/model/constraint_override_model.py
vsc/model/constraint_scope_model.py
vsc/model/constraint_soft_model.py
vsc/model/constraint_solve_order_model.py
vsc/model/constraint_unique_model.py
vsc/model/constraint_unique_vec_model.py
vsc/model/coverage_options_model.py
vsc/model/covergroup_model.py
vsc/model/covergroup_registry.py
vsc/model/coveritem_base.py
vsc/model/coverpoint_bin_array_model.py
vsc/model/coverpoint_bin_collection_model.py
vsc/model/coverpoint_bin_enum_model.py
vsc/model/coverpoint_bin_model_base.py
vsc/model/coverpoint_bin_single_bag_model.py
vsc/model/coverpoint_bin_single_range_model.py
vsc/model/coverpoint_bin_single_val_model.py
vsc/model/coverpoint_bin_single_wildcard_model.py
vsc/model/coverpoint_bin_type.py
vsc/model/coverpoint_cross_model.py
vsc/model/coverpoint_model.py
vsc/model/dist_weight_expr_model.py
vsc/model/enum_field_model.py
vsc/model/expr_array_product_model.py
vsc/model/expr_array_subscript_model.py
vsc/model/expr_array_sum_model.py
vsc/model/expr_bin_model.py
vsc/model/expr_cond_model.py
vsc/model/expr_dynamic_model.py
vsc/model/expr_dynref_model.py
vsc/model/expr_fieldref_model.py
vsc/model/expr_in_model.py
pyvsc-0.9.4.19342806556.dist-info/METADATA
pyvsc-0.9.4.19342806556.dist-info/WHEEL
pyvsc-0.9.4.19342806556.dist-info/entry_points.txt
pyvsc-0.9.4.19342806556.dist-info/top_level.txt
pyvsc-0.9.4.19342806556.dist-info/RECORD
